helga_log_reader/__init__.py
helga_log_reader/plugin.py
helga_log_reader-1.0.4.dist-info/DESCRIPTION.rst
helga_log_reader-1.0.4.dist-info/METADATA
helga_log_reader-1.0.4.dist-info/RECORD
helga_log_reader-1.0.4.dist-info/WHEEL
helga_log_reader-1.0.4.dist-info/entry_points.txt
helga_log_reader-1.0.4.dist-info/metadata.json
helga_log_reader-1.0.4.dist-info/top_level.txt
helga_log_reader-1.0.4.dist-info/zip-safe
tests/__init__.py
tests/test_plugin.py
