Metadata-Version: 2.0
Name: helga-log-reader
Version: 1.0.4
Summary: Read logs from helga bot logging
Home-page: https://github.com/narfman0/helga-log-reader
Author: Jon Robison
Author-email: narfman0@gmail.com
License: LICENSE
Keywords: irc bot log-reader logs
Platform: UNKNOWN
Classifier: Development Status :: 4 - Beta
Classifier: Topic :: Communications :: Chat :: Internet Relay Chat
Classifier: License :: OSI Approved :: GNU General Public License v3 (GPLv3)
Classifier: Operating System :: OS Independent
Classifier: Programming Language :: Python
Classifier: Topic :: Software Development :: Libraries :: Python Modules
Classifier: Topic :: Communications :: Chat :: Internet Relay Chat
Requires-Dist: helga
Requires-Dist: requests
